git_author_stats/__init__.py
git_author_stats/__main__.py
git_author_stats/_github.py
git_author_stats/_stats.py
git_author_stats/py.typed
git_author_stats-1.0.2.dist-info/METADATA
git_author_stats-1.0.2.dist-info/WHEEL
git_author_stats-1.0.2.dist-info/entry_points.txt
git_author_stats-1.0.2.dist-info/RECORD
