Metadata-Version: 2.4
Name: git-author-stats
Version: 1.0.2
Summary: Retrieve multi-repo time series Git stats by author
Project-URL: Documentation, https://git-author-stats.enorganic.org
Project-URL: Repository, https://github.com/enorganic/git-author-stats
Author-email: david@belais.me
License-Expression: MIT
Keywords: git
Requires-Python: ~=3.9
Provides-Extra: github
Requires-Dist: pygithub~=2.6; extra == 'github'
